<?xml version="1.0" encoding="UTF-8"?>
<MediaInfo
    xmlns="https://mediaarea.net/mediainfo"
    xmlns:xsi="http://www.w3.org/2001/XMLSchema-instance"
    xsi:schemaLocation="https://mediaarea.net/mediainfo https://mediaarea.net/mediainfo/mediainfo_2_0.xsd"
    version="2.0">
<creatingLibrary version="17.10" url="https://mediaarea.net/MediaInfo">MediaInfoLib</creatingLibrary>
<media ref="\\STORAGE\Media\Test\Troublesome\ShieldTV - Transcode - Lord of War (2005).mkv">
<track type="General">
<UniqueID>217477456881894349651124406245729665472</UniqueID>
<VideoCount>1</VideoCount>
<AudioCount>1</AudioCount>
<TextCount>1</TextCount>
<MenuCount>1</MenuCount>
<FileExtension>mkv</FileExtension>
<Format>Matroska</Format>
<Format_Version>4</Format_Version>
<FileSize>11149254901</FileSize>
<Duration>7303.337</Duration>
<OverallBitRate>12212779</OverallBitRate>
<FrameRate>23.976</FrameRate>
<FrameCount>175105</FrameCount>
<StreamSize>221859509</StreamSize>
<IsStreamable>No</IsStreamable>
<Encoded_Date>UTC 2017-05-11T12:49:02Z</Encoded_Date>
<File_Created_Date>UTC 2017-10-29 02:52:07.121</File_Created_Date>
<File_Created_Date_Local>2017-10-28 19:52:07.121</File_Created_Date_Local>
<File_Modified_Date>UTC 2017-05-13 00:18:22.827</File_Modified_Date>
<File_Modified_Date_Local>2017-05-12 17:18:22.827</File_Modified_Date_Local>
<Encoded_Application>HandBrake 1.0.7 2017040900</Encoded_Application>
<Encoded_Library>Lavf57.7.2</Encoded_Library>
</track>
<track type="Video">
<StreamOrder>0</StreamOrder>
<ID>1</ID>
<UniqueID>1</UniqueID>
<Format>AVC</Format>
<Format_Profile>High</Format_Profile>
<Format_Level>4</Format_Level>
<Format_Settings_CABAC>Yes</Format_Settings_CABAC>
<Format_Settings_RefFrames>4</Format_Settings_RefFrames>
<CodecID>V_MPEG4/ISO/AVC</CodecID>
<Duration>7303.345</Duration>
<BitRate>10460745</BitRate>
<Width>1920</Width>
<Height>798</Height>
<Stored_Height>800</Stored_Height>
<Sampled_Width>1920</Sampled_Width>
<Sampled_Height>798</Sampled_Height>
<PixelAspectRatio>1.000</PixelAspectRatio>
<DisplayAspectRatio>2.406</DisplayAspectRatio>
<FrameRate_Mode>CFR</FrameRate_Mode>
<FrameRate_Mode_Original>VFR</FrameRate_Mode_Original>
<FrameRate>23.976</FrameRate>
<FrameCount>175105</FrameCount>
<ColorSpace>YUV</ColorSpace>
<ChromaSubsampling>4:2:0</ChromaSubsampling>
<BitDepth>8</BitDepth>
<ScanType>Progressive</ScanType>
<Delay>0.000</Delay>
<StreamSize>9549803451</StreamSize>
<Encoded_Library>x264 - core 148 r2708 86b7198</Encoded_Library>
<Encoded_Library_Name>x264</Encoded_Library_Name>
<Encoded_Library_Version>core 148 r2708 86b7198</Encoded_Library_Version>
<Encoded_Library_Settings>cabac=1 / ref=3 / deblock=1:0:0 / analyse=0x3:0x113 / me=hex / subme=7 / psy=1 / psy_rd=1.00:0.00 / mixed_ref=1 / me_range=16 / chroma_me=1 / trellis=1 / 8x8dct=1 / cqm=0 / deadzone=21,11 / fast_pskip=1 / chroma_qp_offset=-2 / threads=12 / lookahead_threads=2 / sliced_threads=0 / nr=0 / decimate=1 / interlaced=0 / bluray_compat=0 / constrained_intra=0 / bframes=3 / b_pyramid=2 / b_adapt=1 / b_bias=0 / direct=1 / weightb=1 / open_gop=0 / weightp=2 / keyint=240 / keyint_min=24 / scenecut=40 / intra_refresh=0 / rc_lookahead=40 / rc=crf / mbtree=1 / crf=20.0 / qcomp=0.60 / qpmin=0 / qpmax=69 / qpstep=4 / ip_ratio=1.40 / aq=1:1.00</Encoded_Library_Settings>
<Language>en</Language>
<Default>Yes</Default>
<Forced>No</Forced>
<colour_range>Limited</colour_range>
<colour_description_present>Yes</colour_description_present>
<colour_primaries>BT.709</colour_primaries>
<transfer_characteristics>BT.709</transfer_characteristics>
<matrix_coefficients>BT.709</matrix_coefficients>
</track>
<track type="Audio">
<StreamOrder>1</StreamOrder>
<ID>2</ID>
<UniqueID>2</UniqueID>
<Format>DTS</Format>
<Format_Profile>ES Discrete / Core</Format_Profile>
<Format_Settings_Mode>16</Format_Settings_Mode>
<Format_Settings_Endianness>Big</Format_Settings_Endianness>
<CodecID>A_DTS</CodecID>
<Duration>7303.337</Duration>
<BitRate_Mode>CBR</BitRate_Mode>
<BitRate>1509000</BitRate>
<Channels>7 / 6</Channels>
<ChannelPositions>Front: L C R, Side: L R, Back: C, LFE / Front: L C R, Side: L R, LFE</ChannelPositions>
<ChannelLayout>C L R Ls Rs Cs LFE / C L R Ls Rs LFE</ChannelLayout>
<SamplesPerFrame>512</SamplesPerFrame>
<SamplingRate>48000</SamplingRate>
<SamplingCount>350560192</SamplingCount>
<FrameRate>93.750</FrameRate>
<BitDepth>24</BitDepth>
<Compression_Mode>Lossy</Compression_Mode>
<Delay>0.041</Delay>
<Delay_Source>Container</Delay_Source>
<StreamSize>1377591941</StreamSize>
<StreamSize_Proportion>0.12356</StreamSize_Proportion>
<Title>Surround</Title>
<Language>en</Language>
<Default>Yes</Default>
<Forced>No</Forced>
</track>
<track type="Text">
<ID>3</ID>
<UniqueID>3</UniqueID>
<Format>PGS</Format>
<CodecID>S_HDMV/PGS</CodecID>
<Language>en</Language>
<Default>No</Default>
<Forced>No</Forced>
</track>
<track type="Menu">
<extra>
<_00_00_00_165>:Chapter 1</_00_00_00_165>
<_00_08_06_401>:Chapter 2</_00_08_06_401>
<_00_17_26_336>:Chapter 3</_00_17_26_336>
<_00_24_39_268>:Chapter 4</_00_24_39_268>
<_00_32_47_631>:Chapter 5</_00_32_47_631>
<_00_42_11_444>:Chapter 6</_00_42_11_444>
<_00_52_10_042>:Chapter 7</_00_52_10_042>
<_01_00_29_917>:Chapter 8</_01_00_29_917>
<_01_08_51_418>:Chapter 9</_01_08_51_418>
<_01_17_39_820>:Chapter 10</_01_17_39_820>
<_01_24_56_632>:Chapter 11</_01_24_56_632>
<_01_32_35_841>:Chapter 12</_01_32_35_841>
<_01_46_22_291>:Chapter 13</_01_46_22_291>
<_01_54_16_265>:Chapter 14</_01_54_16_265>
</extra>
</track>
</media>
</MediaInfo>
